synthedia/__init__.py
synthedia/__main__.py
synthedia/assembly.py
synthedia/input_reader.py
synthedia/mzml.py
synthedia/peak_models.py
synthedia/peptide.py
synthedia/plotting.py
synthedia/preview.py
synthedia-1.0.3.dist-info/LICENSE
synthedia-1.0.3.dist-info/METADATA
synthedia-1.0.3.dist-info/WHEEL
synthedia-1.0.3.dist-info/entry_points.txt
synthedia-1.0.3.dist-info/top_level.txt
synthedia-1.0.3.dist-info/RECORD
