Metadata-Version: 2.1
Name: synthedia
Version: 1.0.3
Summary: Generate synthetic DIA LC-MS/MS proteomics data
Home-page: https://github.com/mgleeming/synthedia.git
Author: Michael Leeming
Author-email: leemingm@unimelb.edu.au
License: BSD
Classifier: License :: OSI Approved :: BSD License
Classifier: Programming Language :: Python :: 3.8
Classifier: Programming Language :: Python :: 3.9
License-File: LICENSE
Requires-Dist: pandas
Requires-Dist: numpy
Requires-Dist: pyopenms
Requires-Dist: pyteomics
Requires-Dist: matplotlib
Requires-Dist: scipy
Requires-Dist: PyYAML
